sort/__init__.py
sort/bubble_sort.py
sort/insertion_sort.py
sort/quick_sort.py
siwp2005_yonathan_sort-0.1.3.dist-info/LICENSE
siwp2005_yonathan_sort-0.1.3.dist-info/METADATA
siwp2005_yonathan_sort-0.1.3.dist-info/WHEEL
siwp2005_yonathan_sort-0.1.3.dist-info/top_level.txt
siwp2005_yonathan_sort-0.1.3.dist-info/RECORD
